{
  "強気": "强气",
  "効果のスキルカード使用時、": "效果的技能卡使用时，",
  "すべてのスキルカードの": "所有的技能卡的",
  "パラメータ値増加": "打分值增加",
  "+2": "+2",
  "\t ": "\t ",
  "+3": "+3",
  "全力": "全力",
  "全力値": "全力值",
  "<nobr>+": "<nobr>+",
  "1": "1",
  "</nobr>": "</nobr>",
  "次のオーディション開始時、": "下次试镜开始时，",
  "やる気": "干劲",
  "2": "2",
  " ": " ",
  "効果のスキルカードの": "效果的技能卡的",
  "+4": "+4",
  "集中": "集中",
  "好調": "好调",
  "<nobr>": "<nobr>",
  "ターン</nobr>": "回合</nobr>",
  "好印象": "好印象",
  "5": "5",
  "消費体力削減": "削减消耗体力",
  "9": "9",
  "ターン開始時、山札か捨札にあるスキルカードが12枚以上の場合、": "回合开始时，牌堆或弃牌中的技能卡在12张以上时，",
  "スキルカードを引く": "抽取技能卡",
  "パラメータ上昇量増加": "打分上升量增加",
  "%</nobr>": "%</nobr>",
  "+10": "+10",
  "+18": "+18",
  "ターン開始時、山札か捨札にあるスキルカードが18枚以上の場合、": "回合开始时，牌堆或弃牌中的技能卡在18张以上时，",
  "25": "25"
}